__init__.py
pf_client.py
pf_server.py
pyfrost.py
pyfrost_network-0.0.0.dev0.dist-info/LICENSE
pyfrost_network-0.0.0.dev0.dist-info/METADATA
pyfrost_network-0.0.0.dev0.dist-info/WHEEL
pyfrost_network-0.0.0.dev0.dist-info/top_level.txt
pyfrost_network-0.0.0.dev0.dist-info/RECORD
